unique_follow_up_questions/config.py
unique_follow_up_questions/follow_up_postprocessor.py
unique_follow_up_questions/prompts/params.py
unique_follow_up_questions/prompts/suggestions_format.j2
unique_follow_up_questions/prompts/system_prompt.j2
unique_follow_up_questions/prompts/user_prompt.j2
unique_follow_up_questions/schema.py
unique_follow_up_questions/service.py
unique_follow_up_questions/tests/test_config.py
unique_follow_up_questions/tests/test_service.py
unique_follow_up_questions/utils/jinja/helpers.py
unique_follow_up_questions/utils/jinja/render.py
unique_follow_up_questions/utils/jinja/schema.py
unique_follow_up_questions/utils/jinja/utils.py
unique_follow_up_questions-1.1.4.dist-info/LICENSE
unique_follow_up_questions-1.1.4.dist-info/METADATA
unique_follow_up_questions-1.1.4.dist-info/WHEEL
unique_follow_up_questions-1.1.4.dist-info/RECORD
